ha_sync/__init__.py
ha_sync/cli.py
ha_sync/client.py
ha_sync/config.py
ha_sync/models.py
ha_sync/py.typed
ha_sync/render.py
ha_sync/utils.py
ha_sync/sync/__init__.py
ha_sync/sync/automations.py
ha_sync/sync/base.py
ha_sync/sync/config_entries.py
ha_sync/sync/dashboards.py
ha_sync/sync/groups.py
ha_sync/sync/helpers.py
ha_sync/sync/scenes.py
ha_sync/sync/scripts.py
ha_sync/sync/templates.py
ha_sync-0.2.1.dist-info/METADATA
ha_sync-0.2.1.dist-info/WHEEL
ha_sync-0.2.1.dist-info/entry_points.txt
ha_sync-0.2.1.dist-info/licenses/LICENSE
ha_sync-0.2.1.dist-info/RECORD
