Metadata-Version: 2.4
Name: ha-sync
Version: 0.2.1
Summary: Sync Home Assistant UI config (dashboards, automations, helpers) to/from local YAML files
Project-URL: Homepage, https://github.com/DouweM/ha-sync
Project-URL: Repository, https://github.com/DouweM/ha-sync
Project-URL: Issues, https://github.com/DouweM/ha-sync/issues
Author-email: Douwe Maan <hi@douwe.me>
License-Expression: MIT
License-File: LICENSE
Keywords: automation,dashboard,home-assistant,homeassistant,sync,yaml
Classifier: Development Status :: 4 - Beta
Classifier: Environment :: Console
Classifier: Intended Audience :: Developers
Classifier: Intended Audience :: End Users/Desktop
Classifier: License :: OSI Approved :: MIT License
Classifier: Operating System :: OS Independent
Classifier: Programming Language :: Python :: 3
Classifier: Programming Language :: Python :: 3.13
Classifier: Topic :: Home Automation
Requires-Python: >=3.13
Requires-Dist: aiohttp>=3.9
Requires-Dist: httpx>=0.28
Requires-Dist: logfire[httpx]>=4.16.0
Requires-Dist: pydantic-settings>=2.7
Requires-Dist: pydantic>=2.10
Requires-Dist: pyyaml>=6.0
Requires-Dist: rich>=13.9
Requires-Dist: typer>=0.15
Provides-Extra: dev
Requires-Dist: pytest-asyncio>=0.24; extra == 'dev'
Requires-Dist: pytest-mock>=3.14; extra == 'dev'
Requires-Dist: pytest>=8.0; extra == 'dev'
Requires-Dist: respx>=0.22; extra == 'dev'
